{
  "variants": {
    "facing=north,half=upper,open=false": {
      "model": "compendium:block/amberslidingdoor_closed"
    },
    "facing=south,half=upper,open=false": {
      "model": "compendium:block/amberslidingdoor_closed"
    },
    "facing=west,half=upper,open=false": {
      "model": "compendium:block/amberslidingdoor_closed",
      "y": 90
    },
    "facing=east,half=upper,open=false": {
      "model": "compendium:block/amberslidingdoor_closed",
      "y": 90
    },
    "facing=north,half=lower,open=false": {
      "model": "compendium:block/amberslidingdoor_closed"
    },
    "facing=south,half=lower,open=false": {
      "model": "compendium:block/amberslidingdoor_closed"
    },
    "facing=west,half=lower,open=false": {
      "model": "compendium:block/amberslidingdoor_closed",
      "y": 90
    },
    "facing=east,half=lower,open=false": {
      "model": "compendium:block/amberslidingdoor_closed",
      "y": 90
    },
    "facing=north,half=upper,open=true": {
      "model": "compendium:block/amberslidingdoor_open"
    },
    "facing=south,half=upper,open=true": {
      "model": "compendium:block/amberslidingdoor_open"
    },
    "facing=west,half=upper,open=true": {
      "model": "compendium:block/amberslidingdoor_open",
      "y": 90
    },
    "facing=east,half=upper,open=true": {
      "model": "compendium:block/amberslidingdoor_open",
      "y": 90
    },
    "facing=north,half=lower,open=true": {
      "model": "compendium:block/amberempty"
    },
    "facing=south,half=lower,open=true": {
      "model": "compendium:block/amberempty"
    },
    "facing=west,half=lower,open=true": {
      "model": "compendium:block/amberempty"
    },
    "facing=east,half=lower,open=true": {
      "model": "compendium:block/amberempty"
    }
  }
}