{
  "parent": "minecraft:recipes/root",
  "rewards": {
    "recipes": [
      "compendium:electrum_sword"
    ]
  },
  "criteria": {
    "electrumingot": {
      "trigger": "minecraft:inventory_changed",
      "conditions": {
        "items": [
          {
            "tag": "forge:ingots/electrum"
          }
        ]
      }
    },
    "has_the_recipe": {
      "trigger": "minecraft:recipe_unlocked",
      "conditions": {
        "recipe": "compendium:electrum_sword"
      }
    }
  },
  "requirements": [
    [
      "electrumingot",
      "has_the_recipe"
    ]
  ]
}