{
  "parent": "minecraft:recipes/root",
  "rewards": {
    "recipes": [
      "minecraft:topazgem_from_ore_furnace"
    ]
  },
  "criteria": {
    "topazore": {
      "trigger": "minecraft:inventory_changed",
      "conditions": {
        "items": [
          {
            "item": "compendium:topazitemore"
          }
        ]
      }
    },
    "has_the_recipe": {
      "trigger": "minecraft:recipe_unlocked",
      "conditions": {
        "recipe": "minecraft:topazgem_from_ore_furnace"
      }
    }
  },
  "requirements": [
    [
      "topazore",
      "has_the_recipe"
    ]
  ]
}