{
  "type": "minecraft:crafting_shapeless",
  "ingredients": [
    {
      "tag": "forge:nugget/lead"
    },
    {
      "tag": "forge:nugget/lead"
    },
    {
      "tag": "forge:nugget/lead"
    },
    {
      "tag": "forge:nugget/lead"
    },
    {
      "tag": "forge:nugget/lead"
    },
    {
      "tag": "forge:nugget/lead"
    },
    {
      "tag": "forge:nugget/lead"
    },
    {
      "tag": "forge:nugget/lead"
    },
    {
      "tag": "forge:nugget/lead"
    }
  ],
  "result": {
    "item": "compendium:lead_ingot"
  }
}