{
  "type": "minecraft:crafting_shapeless",
  "ingredients": [
    {
      "item": "compendium:rosegoldingot"
    },
    {
      "item": "compendium:rosegoldingot"
    },
    {
      "item": "compendium:rosegoldingot"
    },
    {
      "item": "compendium:rosegoldingot"
    },
    {
      "item": "compendium:rosegoldingot"
    },
    {
      "item": "compendium:rosegoldingot"
    },
    {
      "item": "compendium:rosegoldingot"
    },
    {
      "item": "compendium:rosegoldingot"
    },
    {
      "item": "compendium:rosegoldingot"
    }
  ],
  "result": {
    "item": "compendium:rosegolditemblock"
  }
}