{
  "type": "minecraft:crafting_shapeless",
  "ingredients": [
    {
      "tag": "compendium:nuggets/abyssalium"
    },
    {
      "tag": "compendium:nuggets/abyssalium"
    },
    {
      "tag": "compendium:nuggets/abyssalium"
    },
    {
      "tag": "compendium:nuggets/abyssalium"
    },
    {
      "tag": "compendium:nuggets/abyssalium"
    },
    {
      "tag": "compendium:nuggets/abyssalium"
    },
    {
      "tag": "compendium:nuggets/abyssalium"
    },
    {
      "tag": "compendium:nuggets/abyssalium"
    },
    {
      "tag": "compendium:nuggets/abyssalium"
    }
  ],
  "result": {
    "item": "compendium:abyssaliumingot"
  }
}