{
  "parent": "minecraft:recipes/root",
  "rewards": {
    "recipes": [
      "compendium:dogbearium_casing_from_plates"
    ]
  },
  "criteria": {
    "dogbeariumcasing": {
      "trigger": "minecraft:inventory_changed",
      "conditions": {
        "items": [
          {
            "item": "compendium:dogbeariumplate"
          }
        ]
      }
    },
    "has_the_recipe": {
      "trigger": "minecraft:recipe_unlocked",
      "conditions": {
        "recipe": "compendium:dogbearium_casing_from_plates"
      }
    }
  },
  "requirements": [
    [
      "dogbeariumcasing",
      "has_the_recipe"
    ]
  ]
}